ngbpm/__init__.py
ngbpm/api.py
ngbpm/app.py
ngbpm/cli.py
ngbpm/experiments/__init__.py
ngbpm/experiments/aggregates_main.py
ngbpm/experiments/bpel_messages.py
ngbpm/experiments/rddd_messages.yaml
ngbpm/experiments/reports/pytest.xml
ngbpm/modules/__init__.py
ngbpm/rddd/__init__.py
ngbpm/rddd/aggregates/__init__.py
ngbpm/rddd/aggregates/activity_execution_aggregate.py
ngbpm/rddd/aggregates/partner_interaction_aggregate.py
ngbpm/rddd/aggregates/process_execution_aggregate.py
ngbpm/rddd/aggregates/process_instance_aggregate.py
ngbpm/rddd/messages.py
ngbpm/subcommands/__init__.py
ngbpm-2024.3.10.3.dist-info/LICENSE
ngbpm-2024.3.10.3.dist-info/METADATA
ngbpm-2024.3.10.3.dist-info/WHEEL
ngbpm-2024.3.10.3.dist-info/entry_points.txt
ngbpm-2024.3.10.3.dist-info/RECORD
